xj_push/__init__.py
xj_push/admin.py
xj_push/apps.py
xj_push/common.py
xj_push/models.py
xj_push/service_register.py
xj_push/urls.py
xj_push/apis/__init__.py
xj_push/apis/push_apis.py
xj_push/apis/push_plan_apis.py
xj_push/apis/push_push_apis.py
xj_push/apis/push_record_apis.py
xj_push/apis/push_single_apis.py
xj_push/apis/push_template_apis.py
xj_push/management/__init__.py
xj_push/management/commands/__init__.py
xj_push/management/commands/push_test.py
xj_push/orator_models/__init__.py
xj_push/orator_models/base_model.py
xj_push/orator_models/push_plan.py
xj_push/orator_models/push_template.py
xj_push/push_pipeline/__init__.py
xj_push/push_pipeline/bx_custom_pipeline.py
xj_push/push_pipeline/bx_visitor_pipeline.py
xj_push/push_pipeline/bx_worker_pipeline.py
xj_push/push_pipeline/pipline_base.py
xj_push/push_pipeline/single_push_pipeline.py
xj_push/services/__init__.py
xj_push/services/push_plan_service.py
xj_push/services/push_record_service.py
xj_push/services/push_service.py
xj_push/services/push_single_service.py
xj_push/services/push_template_main_service.py
xj_push/services/push_template_service.py
xj_push/utils/__init__.py
xj_push/utils/common.py
xj_push/utils/custom_response.py
xj_push/utils/custom_tool.py
xj_push/utils/j_config.py
xj_push/utils/j_dict.py
xj_push/utils/j_recur.py
xj_push/utils/model_handle.py
xj_push/utils/service_manager.py
xj_push/utils/user_wrapper.py
xj_push/utils/utility_method.py
xj_push/utils/utils.py
xj_push/utils/wechat.py
xj_push-1.0.34.dist-info/METADATA
xj_push-1.0.34.dist-info/WHEEL
xj_push-1.0.34.dist-info/top_level.txt
xj_push-1.0.34.dist-info/RECORD
