Metadata-Version: 2.1
Name: xj_push
Version: 1.0.34
Summary: 推送模块
License: apache 3.0
